yin_test_upload/__init__.py
yin_test_upload/test.py
yin_test_upload-0.1.12.dist-info/METADATA
yin_test_upload-0.1.12.dist-info/WHEEL
yin_test_upload-0.1.12.dist-info/top_level.txt
yin_test_upload-0.1.12.dist-info/RECORD
