Metadata-Version: 2.1
Name: yin-test-upload
Version: 0.1.12
Summary: 脚本打包
Author: yin
Author-email: 2018209921@qq.com
Requires-Python: >3.9
